<?xml version="1.0" ?>
<TLFSemanticImageDescriptor ImageWidth="0" ImageHeight="0">
    <TLFDetectedItem DetectorName="Human marked" Raiting="0.000000" Type="20D25B0E-0963-4414-8DF9-A695E30A7A45" Angle="0" Racurs="0" Bw="12" Bh="24" left="34" top="66" right="53" bottom="104" Comment="" />
    <TLFDetectedItem DetectorName="Human marked" Raiting="0.000000" Type="7E25FCA7-CCE4-4FE6-A22C-84AD3E197624" Angle="0" Racurs="0" Bw="12" Bh="24" left="57" top="64" right="77" bottom="104" Comment="" />
    <TLFDetectedItem DetectorName="Human marked" Raiting="0.000000" Type="7E25FCA7-CCE4-4FE6-A22C-84AD3E197624" Angle="0" Racurs="0" Bw="12" Bh="24" left="79" top="64" right="99" bottom="104" Comment="" />
    <TLFDetectedItem DetectorName="Human marked" Raiting="0.000000" Type="7E25FCA7-CCE4-4FE6-A22C-84AD3E197624" Angle="0" Racurs="0" Bw="12" Bh="24" left="100" top="64" right="120" bottom="104" Comment="" />
    <TLFDetectedItem DetectorName="Human marked" Raiting="0.000000" Type="B8A8F9E9-1762-46D6-B11A-C2750F0947CE" Angle="0" Racurs="0" Bw="12" Bh="24" left="126" top="65" right="145" bottom="103" Comment="" />
    <TLFDetectedItem DetectorName="Human marked" Raiting="0.000000" Type="B8A8F9E9-1762-46D6-B11A-C2750F0947CE" Angle="0" Racurs="0" Bw="12" Bh="24" left="147" top="65" right="166" bottom="103" Comment="" />
    <TLFDetectedItem DetectorName="Human marked" Raiting="0.000000" Type="B3B9E4D5-F246-4CDE-A9DC-0A13DBF84D7D" Angle="0" Racurs="0" Bw="12" Bh="24" left="176" top="58" right="193" bottom="92" Comment="" />
    <TLFDetectedItem DetectorName="Human marked" Raiting="0.000000" Type="C3D67EE7-9577-4701-A4E0-30FEE8029D19" Angle="0" Racurs="0" Bw="12" Bh="24" left="195" top="57" right="212" bottom="91" Comment="" />
</TLFSemanticImageDescriptor>
