<?xml version="1.0" ?>
<TLFSemanticImageDescriptor ImageWidth="0" ImageHeight="0">
    <TLFDetectedItem DetectorName="Human marked" Raiting="0.000000" Type="B8A8F9E9-1762-46D6-B11A-C2750F0947CE" Angle="0" Racurs="0" Bw="12" Bh="24" left="36" top="27" right="53" bottom="61" Comment="" />
    <TLFDetectedItem DetectorName="Human marked" Raiting="0.000000" Type="401E303C-5C3E-4597-8D0C-B98D6856312C" Angle="0" Racurs="0" Bw="12" Bh="24" left="55" top="25" right="74" bottom="63" Comment="" />
    <TLFDetectedItem DetectorName="Human marked" Raiting="0.000000" Type="0CC617C3-A84D-4E81-B8BC-AD3FF4FAEDA2" Angle="0" Racurs="0" Bw="12" Bh="24" left="75" top="26" right="93" bottom="62" Comment="" />
    <TLFDetectedItem DetectorName="Human marked" Raiting="0.000000" Type="C3D67EE7-9577-4701-A4E0-30FEE8029D19" Angle="0" Racurs="0" Bw="12" Bh="24" left="94" top="26" right="112" bottom="62" Comment="" />
    <TLFDetectedItem DetectorName="Human marked" Raiting="0.000000" Type="25BCB5A7-E000-4E91-910D-9492F5D9B3B9" Angle="0" Racurs="0" Bw="12" Bh="24" left="114" top="29" right="130" bottom="61" Comment="" />
    <TLFDetectedItem DetectorName="Human marked" Raiting="0.000000" Type="FB118348-7928-4BAD-BB64-F031BF4CFC45" Angle="0" Racurs="0" Bw="12" Bh="24" left="133" top="27" right="151" bottom="63" Comment="" />
    <TLFDetectedItem DetectorName="Human marked" Raiting="0.000000" Type="FCA67A0D-C031-4EFC-90A3-1B07676190B0" Angle="0" Racurs="0" Bw="12" Bh="24" left="157" top="26" right="171" bottom="54" Comment="" />
    <TLFDetectedItem DetectorName="Human marked" Raiting="0.000000" Type="C3D67EE7-9577-4701-A4E0-30FEE8029D19" Angle="0" Racurs="0" Bw="12" Bh="24" left="172" top="26" right="186" bottom="54" Comment="" />
    <TLFDetectedItem DetectorName="Human marked" Raiting="0.000000" Type="7E25FCA7-CCE4-4FE6-A22C-84AD3E197624" Angle="0" Racurs="0" Bw="12" Bh="24" left="186" top="26" right="200" bottom="54" Comment="" />
</TLFSemanticImageDescriptor>
