<?xml version="1.0" ?>
<TLFSemanticImageDescriptor ImageWidth="0" ImageHeight="0">
    <TLFDetectedItem DetectorName="Human marked" Raiting="0.000000" Type="3CE813FA-F606-46D9-922C-EC3DFC7AF41B" Angle="0" Racurs="0" Bw="12" Bh="24" left="38" top="26" right="54" bottom="58" Comment="" />
    <TLFDetectedItem DetectorName="Human marked" Raiting="0.000000" Type="C3D67EE7-9577-4701-A4E0-30FEE8029D19" Angle="0" Racurs="0" Bw="12" Bh="24" left="60" top="23" right="78" bottom="59" Comment="" />
    <TLFDetectedItem DetectorName="Human marked" Raiting="0.000000" Type="401E303C-5C3E-4597-8D0C-B98D6856312C" Angle="0" Racurs="0" Bw="12" Bh="24" left="79" top="23" right="97" bottom="59" Comment="" />
    <TLFDetectedItem DetectorName="Human marked" Raiting="0.000000" Type="401E303C-5C3E-4597-8D0C-B98D6856312C" Angle="0" Racurs="0" Bw="12" Bh="24" left="100" top="23" right="118" bottom="59" Comment="" />
    <TLFDetectedItem DetectorName="Human marked" Raiting="0.000000" Type="FB118348-7928-4BAD-BB64-F031BF4CFC45" Angle="0" Racurs="0" Bw="12" Bh="24" left="122" top="27" right="139" bottom="61" Comment="" />
    <TLFDetectedItem DetectorName="Human marked" Raiting="0.000000" Type="F4038872-5489-4743-9AD1-E75AEA0B93D3" Angle="0" Racurs="0" Bw="12" Bh="24" left="142" top="23" right="161" bottom="61" Comment="" />
    <TLFDetectedItem DetectorName="Human marked" Raiting="0.000000" Type="401E303C-5C3E-4597-8D0C-B98D6856312C" Angle="0" Racurs="0" Bw="12" Bh="24" left="168" top="25" right="182" bottom="53" Comment="" />
    <TLFDetectedItem DetectorName="Human marked" Raiting="0.000000" Type="B3B9E4D5-F246-4CDE-A9DC-0A13DBF84D7D" Angle="0" Racurs="0" Bw="12" Bh="24" left="184" top="25" right="199" bottom="55" Comment="" />
</TLFSemanticImageDescriptor>
